{
  "posts": [
    {
      "id": 1,
      "title": "Hello World",
      "body": "Quia et suscipit\nsuscipit recusandae consequuntur expedita et cum\nreprehenderit molestiae ut ut quas totam\nnostrum rerum est autem sunt rem eveniet architecto"
    },
    {
      "id": 2,
      "title": "Eum Et Est Occaecati",
      "body": "Recusandae consequuntur expedita et cum\nreprehenderit ut quas totam\nautem sunt rem eveniet architecto"
    }
  ],
  "users": [
    {
      "id": 1,
      "name": "Chandra",
      "age": 29,
      "place": "Visakhapatnam",
      "batch_name": "WEB-21",
      "profession": "FSD"
    },
    {
      "id": 1,
      "name": "Nrupul",
      "age": 32,
      "place": "Vijayawada",
      "batch_name": "WEB-18",
      "profession": "FSD"
    }
  ],
  "dogs": [
    {
      "id": 1,
      "name": "Cherry",
      "age": 2,
      "place": "Visakhapatnam",
      "gender": "Male"
    },
    {
      "id": 2,
      "name": "Tommy",
      "age": 3,
      "place": "Banglore",
      "gender": "Female"
    },
    {
      "id": 3,
      "name": "Rinku",
      "age": 2,
      "place": "kolhapur",
      "gender": "Female"
    },
    {
      "id": 4,
      "name": "Coco",
      "age": 1,
      "place": "Pune",
      "gender": "Male"
    },
    {
      "id": 5,
      "name": "Juju",
      "age": 5,
      "place": "Patna",
      "gender": "Female"
    },
    {
      "id": 6,
      "name": "Rocky",
      "age": 7,
      "place": "Hydrabad",
      "gender": "Female"
    }
  ]
}
